Metadata-Version: 1.0
Name: jinbotron
Version: 0.1
Summary: The most interactive bot you got.
Home-page: http://www.facebook.com/YujinYuz
Author: yujinyuz
Author-email: jinyuzprodigy@gmail.com
License: MIT
Platform: UNKNOWN
